.gitignore
MANIFEST.in
README.rst
setup.py
docs/HISTORY.rst
docs/LICENSE
src/sphinx/__init__.py
src/sphinx.themes.plone.egg-info/PKG-INFO
src/sphinx.themes.plone.egg-info/SOURCES.txt
src/sphinx.themes.plone.egg-info/dependency_links.txt
src/sphinx.themes.plone.egg-info/entry_points.txt
src/sphinx.themes.plone.egg-info/namespace_packages.txt
src/sphinx.themes.plone.egg-info/not-zip-safe
src/sphinx.themes.plone.egg-info/requires.txt
src/sphinx.themes.plone.egg-info/top_level.txt
src/sphinx/themes/__init__.py
src/sphinx/themes/plone/__init__.py
src/sphinx/themes/plone/plone_basic/doormat.html
src/sphinx/themes/plone/plone_basic/footer.html
src/sphinx/themes/plone/plone_basic/header.html
src/sphinx/themes/plone/plone_basic/layout.html
src/sphinx/themes/plone/plone_basic/searchbox.html
src/sphinx/themes/plone/plone_basic/theme.conf
src/sphinx/themes/plone/plone_basic/topbar.html
src/sphinx/themes/plone/plone_basic/versions.html
src/sphinx/themes/plone/plone_basic/static/css/admonition.css
src/sphinx/themes/plone/plone_basic/static/css/bootstrap-theme.css
src/sphinx/themes/plone/plone_basic/static/css/bootstrap-theme.css.map
src/sphinx/themes/plone/plone_basic/static/css/bootstrap-theme.min.css
src/sphinx/themes/plone/plone_basic/static/css/bootstrap.css
src/sphinx/themes/plone/plone_basic/static/css/bootstrap.css.map
src/sphinx/themes/plone/plone_basic/static/css/bootstrap.min.css
src/sphinx/themes/plone/plone_basic/static/css/font-awesome.css
src/sphinx/themes/plone/plone_basic/static/css/font-awesome.min.css
src/sphinx/themes/plone/plone_basic/static/css/plone-fonts.css
src/sphinx/themes/plone/plone_basic/static/css/ploneorg4.css
src/sphinx/themes/plone/plone_basic/static/css/ploneorg5.css
src/sphinx/themes/plone/plone_basic/static/fonts/DINBlack.eot
src/sphinx/themes/plone/plone_basic/static/fonts/DINBlack.otf
src/sphinx/themes/plone/plone_basic/static/fonts/DINBlack.suit
src/sphinx/themes/plone/plone_basic/static/fonts/DINBlack.svg
src/sphinx/themes/plone/plone_basic/static/fonts/DINBlack.woff
src/sphinx/themes/plone/plone_basic/static/fonts/DINBold.eot
src/sphinx/themes/plone/plone_basic/static/fonts/DINBold.otf
src/sphinx/themes/plone/plone_basic/static/fonts/DINBold.suit
src/sphinx/themes/plone/plone_basic/static/fonts/DINBold.svg
src/sphinx/themes/plone/plone_basic/static/fonts/DINBold.woff
