Metadata-Version: 1.1
Name: sphinx.themes.plone
Version: 0.1.1
Summary: Collection of Sphinx Themes for Plone Documentations
Home-page: https://github.com/plone/sphinx.themes.plone.git
Author: Alexander Loechel on behalf of Plone Foundation
Author-email: Alexander.Loechel@lmu.de
License: GPL
Keywords: sphinx plone themes
Platform: UNKNOWN
Classifier: Programming Language :: Python
Classifier: Framework :: Plone
Classifier: License :: OSI Approved :: GNU General Public License (GPL)
Classifier: Topic :: Software Development :: Documentation
Classifier: Operating System :: OS Independent
Classifier: Development Status :: 5 - Production/Stable
Classifier: Environment :: Web Environment
Classifier: Intended Audience :: Developers
